{
  "client_machine": "m6i.8xlarge, 10000gib gp3",
  "server_system": "ClickHouse Cloud 24.10 30 vCPU and 120 GiB per replica / 3 replicas",
  "date": "2025-02-18",
  "interface": "http",
  "format": "Protobuf",
  "total_num_rows": 10000000,
  "batch_size": 500000,
  "sorted": true,
  "compressor": "lz4",
  "compression_type": "http compression",
  "server_metrics": {
    "db_name:": "hits_http_protobuf_500000_sorted_lz4_2025_02_18_15_28",
    "table_name:": "hits",
    "used_interface:": "http",
    "used_transport_format:": "Protobuf",
    "inserts:": 20,
    "rows_per_insert:": 500000,
    "total_inserted_rows:": 10000000,
    "total_time_including_client_loop_s:": 82,
    "total_received_bytes:": 2923102484,
    "received_bytes_per_insert:": 146155124,
    "total_received_bytes_readable:": "2.72 GiB",
    "received_bytes_per_insert_readable:": "139.38 MiB",
    "total_written_bytes_compressed:": 1570984755,
    "written_bytes_compressed_per_insert:": 78549238,
    "total_written_bytes_compressed_readable:": "1.46 GiB",
    "written_bytes_compressed_per_insert_readable:": "74.91 MiB",
    "total_insert_duration_s:": 65.05,
    "total_network_receive_duration_s:": 1.64,
    "total_block_sort_duration_s:": 0.1,
    "total_storage_write_duration_s:": 26.81,
    "total_cpu_s:": 60.7,
    "num_delayed_inserts:": 0,
    "total_delayed_inserts_ms:": 0,
    "insert_duration_ms_50th:": 3243,
    "insert_duration_ms_95th:": 3378.45,
    "insert_duration_ms_99th:": 3415.69,
    "network_receive_duration_ms_50th:": 79.89,
    "network_receive_duration_ms_95th:": 103.48,
    "network_receive_duration_ms_99th:": 110.13,
    "block_sort_duration_ms_50th:": 4.96,
    "block_sort_duration_ms_95th:": 5.04,
    "block_sort_duration_ms_99th:": 5.07,
    "storage_write_duration_ms_50th:": 1331.8,
    "storage_write_duration_ms_95th:": 1436.31,
    "storage_write_duration_ms_99th:": 1545.28,
    "network_received_bytes_50th:": 146119359,
    "network_received_bytes_95th:": 146405620,
    "network_received_bytes_99th:": 146407650,
    "network_received_bytes_50th_readable:": "139.35 MiB",
    "network_received_bytes_95th_readable:": "139.62 MiB",
    "network_received_bytes_99th_readable:": "139.63 MiB",
    "mergetree_written_uncompressed_bytes_50th:": 412210550,
    "mergetree_written_uncompressed_bytes_95th:": 412637580,
    "mergetree_written_uncompressed_bytes_99th:": 412669181,
    "mergetree_written_uncompressed_bytes_50th_readable:": "393.11 MiB",
    "mergetree_written_uncompressed_bytes_95th_readable:": "393.52 MiB",
    "mergetree_written_uncompressed_bytes_99th_readable:": "393.55 MiB",
    "mergetree_written_compressed_bytes_50th:": 78555622,
    "mergetree_written_compressed_bytes_95th:": 78684563,
    "mergetree_written_compressed_bytes_99th:": 78685329,
    "mergetree_written_compressed_bytes_50th_readable:": "74.92 MiB",
    "mergetree_written_compressed_bytes_95th_readable:": "75.04 MiB",
    "mergetree_written_compressed_bytes_99th_readable:": "75.04 MiB",
    "memory_usage_bytes_50th:": 1036079297,
    "memory_usage_bytes_95th:": 1036610692,
    "memory_usage_bytes_99th:": 1036634304,
    "memory_usage_50th_readable:": "988.08 MiB",
    "memory_usage_95th_readable:": "988.59 MiB",
    "memory_usage_99th_readable:": "988.61 MiB",
    "cpu_ms_50th:": 3040.01,
    "cpu_ms_95th:": 3117.27,
    "cpu_ms_99th:": 3157.54,
    "num_used_threads_50th:": 12,
    "num_used_threads_95th:": 12,
    "num_used_threads_99th:": 12,
    "num_used_threads_concurrently_50th:": 12,
    "num_used_threads_concurrently_95th:": 12,
    "num_used_threads_concurrently_99th:": 12,
    "profileevents_sample:": "{'Query':1,'InsertQuery':1,'InitialQuery':1,'FileOpen':12,'WriteBufferFromFileDescriptorWrite':21,'WriteBufferFromFileDescriptorWriteBytes':78570095,'IOBufferAllocs':25,'IOBufferAllocBytes':105125415,'FunctionExecute':105,'DiskWriteElapsedMicroseconds':43170,'NetworkReceiveElapsedMicroseconds':76212,'NetworkReceiveBytes':146204047,'LocalThreadPoolJobs':11,'InsertedRows':500000,'InsertedBytes':412358911,'ZooKeeperTransactions':8,'ZooKeeperCreate':1,'ZooKeeperRemove':1,'ZooKeeperExists':1,'ZooKeeperMulti':5,'SelectedRows':500000,'SelectedBytes':412358911,'MergeTreeDataWriterRows':500000,'MergeTreeDataWriterUncompressedBytes':412358911,'MergeTreeDataWriterCompressedBytes':78564620,'MergeTreeDataWriterBlocks':1,'MergeTreeDataWriterBlocksAlreadySorted':1,'MergeTreeDataWriterSortingBlocksMicroseconds':4982,'MergeTreeDataWriterMergingBlocksMicroseconds':5,'InsertedCompactParts':1,'ContextLock':37,'RWLockAcquiredReadLocks':2,'PartsLockHoldMicroseconds':182,'RealTimeMicroseconds':4421733,'UserTimeMicroseconds':2633996,'SystemTimeMicroseconds':449491,'SoftPageFaults':260165,'OSCPUWaitMicroseconds':336,'OSCPUVirtualTimeMicroseconds':3083479,'OSWriteBytes':78606336,'OSReadChars':54116,'OSWriteChars':157461620,'QueryProfilerRuns':3,'S3WriteMicroseconds':1042443,'S3WriteRequestsCount':13,'DiskS3WriteMicroseconds':1042443,'DiskS3WriteRequestsCount':13,'S3CreateMultipartUpload':1,'S3UploadPart':3,'S3CompleteMultipartUpload':1,'S3PutObject':8,'DiskS3CreateMultipartUpload':1,'DiskS3UploadPart':3,'DiskS3CompleteMultipartUpload':1,'DiskS3PutObject':8,'WriteBufferFromS3Microseconds':1271392,'WriteBufferFromS3Bytes':78567097,'CachedWriteBufferCacheWriteBytes':78567097,'CachedWriteBufferCacheWriteMicroseconds':44587,'FilesystemCacheLockKeyMicroseconds':1,'FilesystemCacheReserveMicroseconds':764,'FileSegmentCompleteMicroseconds':35,'FileSegmentWriteMicroseconds':43555,'FilesystemCacheHoldFileSegments':11,'FilesystemCacheUnusedHoldFileSegments':11,'MetadataFromKeeperCacheHit':8,'MetadataFromKeeperCacheMiss':5,'MetadataFromKeeperTransactionCommit':1,'MetadataFromKeeperOperations':5,'MetadataFromKeeperIndividualOperations':4,'SharedMergeTreeMetadataCacheHintLoadedFromCache':1,'LogTrace':43,'LogDebug':8,'LoggerElapsedNanoseconds':778480,'InterfaceHTTPReceiveBytes':146204047,'DiskConnectionsCreated':7,'DiskConnectionsReused':6,'DiskConnectionsPreserved':13,'DiskConnectionsElapsedMicroseconds':29201,'HTTPConnectionsReused':1,'HTTPConnectionsPreserved':1,'ReadWriteBufferFromHTTPRequestsSent':1,'ReadWriteBufferFromHTTPBytes':2599}"
  },
  "cpu_memory_usage": "[(1,3.05,1036095460,'988.10 MiB'),(2,3.03,1036549243,'988.53 MiB'),(3,3.08,1036336565,'988.33 MiB'),(4,3.02,1036394385,'988.38 MiB'),(5,2.97,1036280337,'988.27 MiB'),(6,3.07,1035887100,'987.90 MiB'),(7,3.1,1032313686,'984.49 MiB'),(8,3.11,1031911247,'984.11 MiB'),(9,2.99,1035923935,'987.93 MiB'),(10,3.01,1036043135,'988.05 MiB'),(11,2.94,1031998431,'984.19 MiB'),(12,2.85,1036434576,'988.42 MiB'),(13,3.03,1036063134,'988.07 MiB'),(14,3.07,1036609139,'988.59 MiB'),(15,3.04,1031876068,'984.07 MiB'),(16,3.17,1036640207,'988.62 MiB'),(17,3.05,1036130759,'988.13 MiB'),(18,3.04,1032007220,'984.20 MiB'),(19,3.05,1031548487,'983.76 MiB'),(20,3.03,1036154680,'988.15 MiB')]"
}
