{
  "client_machine": "m6i.8xlarge, 10000gib gp3",
  "server_system": "ClickHouse Cloud 24.10 30 vCPU and 120 GiB per replica / 3 replicas",
  "date": "2025-02-26",
  "interface": "http",
  "format": "JSONCompactEachRow",
  "total_num_rows": 10000000,
  "batch_size": 500000,
  "sorted": false,
  "compressor": "zstd",
  "compression_type": "http compression",
  "server_metrics": {
    "db_name": "hits_http_jsoncompacteachrow_500000_zstd_2025_02_27_05_23",
    "table_name": "hits",
    "used_interface": "http",
    "used_transport_format": "JSONCompactEachRow",
    "inserts": 20,
    "rows_per_insert": 500000,
    "total_inserted_rows": 10000000,
    "total_time_including_client_loop_s": 111,
    "total_received_bytes": 2593855189,
    "received_bytes_per_insert": 129692759,
    "total_received_bytes_readable": "2.42 GiB",
    "received_bytes_per_insert_readable": "123.68 MiB",
    "total_written_bytes_compressed": 1593028523,
    "written_bytes_compressed_per_insert": 79651426,
    "total_written_bytes_compressed_readable": "1.48 GiB",
    "written_bytes_compressed_per_insert_readable": "75.96 MiB",
    "total_insert_duration_s": 63.88,
    "total_network_receive_duration_s": 0.84,
    "total_block_sort_duration_s": 0.6,
    "total_storage_write_duration_s": 31.85,
    "total_cpu_s": 117.85,
    "num_delayed_inserts": 0,
    "total_delayed_inserts_ms": 0,
    "insert_duration_ms_50th": 3165,
    "insert_duration_ms_95th": 3372.35,
    "insert_duration_ms_99th": 3575.27,
    "network_receive_duration_ms_50th": 41.26,
    "network_receive_duration_ms_95th": 45.69,
    "network_receive_duration_ms_99th": 50.63,
    "block_sort_duration_ms_50th": 29.94,
    "block_sort_duration_ms_95th": 31.17,
    "block_sort_duration_ms_99th": 32,
    "storage_write_duration_ms_50th": 1561.43,
    "storage_write_duration_ms_95th": 1808.05,
    "storage_write_duration_ms_99th": 1959.72,
    "network_received_bytes_50th": 129683878,
    "network_received_bytes_95th": 129860982,
    "network_received_bytes_99th": 129872991,
    "network_received_bytes_50th_readable": "123.68 MiB",
    "network_received_bytes_95th_readable": "123.85 MiB",
    "network_received_bytes_99th_readable": "123.86 MiB",
    "mergetree_written_uncompressed_bytes_50th": 311024238,
    "mergetree_written_uncompressed_bytes_95th": 317908226,
    "mergetree_written_uncompressed_bytes_99th": 393256895,
    "mergetree_written_uncompressed_bytes_50th_readable": "296.62 MiB",
    "mergetree_written_uncompressed_bytes_95th_readable": "303.18 MiB",
    "mergetree_written_uncompressed_bytes_99th_readable": "375.04 MiB",
    "mergetree_written_compressed_bytes_50th": 79615253,
    "mergetree_written_compressed_bytes_95th": 79824331,
    "mergetree_written_compressed_bytes_99th": 80202786,
    "mergetree_written_compressed_bytes_50th_readable": "75.93 MiB",
    "mergetree_written_compressed_bytes_95th_readable": "76.13 MiB",
    "mergetree_written_compressed_bytes_99th_readable": "76.49 MiB",
    "memory_usage_bytes_50th": 1137136038,
    "memory_usage_bytes_95th": 1146714737,
    "memory_usage_bytes_99th": 1234886943,
    "memory_usage_50th_readable": "1.06 GiB",
    "memory_usage_95th_readable": "1.07 GiB",
    "memory_usage_99th_readable": "1.15 GiB",
    "cpu_ms_50th": 5894.62,
    "cpu_ms_95th": 6038.95,
    "cpu_ms_99th": 6047.7,
    "num_used_threads_50th": 18,
    "num_used_threads_95th": 19.300000000000004,
    "num_used_threads_99th": 23.859999999999992,
    "num_used_threads_concurrently_50th": 12,
    "num_used_threads_concurrently_95th": 12,
    "num_used_threads_concurrently_99th": 12,
    "profileevents_sample": "{'Query':1,'InsertQuery':1,'InitialQuery':1,'FileOpen':12,'WriteBufferFromFileDescriptorWrite':25,'WriteBufferFromFileDescriptorWriteBytes':79420269,'IOBufferAllocs':70,'IOBufferAllocBytes':458730470,'FunctionExecute':210,'DiskWriteElapsedMicroseconds':35474,'NetworkReceiveElapsedMicroseconds':40150,'NetworkReceiveBytes':129486972,'GlobalThreadPoolJobs':5,'LocalThreadPoolExpansions':4,'LocalThreadPoolThreadCreationMicroseconds':54,'LocalThreadPoolJobs':56,'InsertedRows':500000,'InsertedBytes':310590217,'ZooKeeperTransactions':12,'ZooKeeperCreate':2,'ZooKeeperRemove':2,'ZooKeeperMulti':8,'SelectedRows':500000,'SelectedBytes':310590217,'MergeTreeDataWriterRows':500000,'MergeTreeDataWriterUncompressedBytes':310569763,'MergeTreeDataWriterCompressedBytes':79415024,'MergeTreeDataWriterBlocks':2,'MergeTreeDataWriterSortingBlocksMicroseconds':29087,'MergeTreeDataWriterMergingBlocksMicroseconds':7,'InsertedCompactParts':2,'ContextLock':49,'RWLockAcquiredReadLocks':2,'PartsLockHoldMicroseconds':283,'RealTimeMicroseconds':9011587,'UserTimeMicroseconds':5467019,'SystemTimeMicroseconds':350342,'SoftPageFaults':331596,'OSCPUWaitMicroseconds':1969,'OSCPUVirtualTimeMicroseconds':5817290,'OSWriteBytes':79462400,'OSReadChars':123858,'OSWriteChars':159187633,'QueryProfilerRuns':15,'S3WriteMicroseconds':1401930,'S3WriteRequestsCount':14,'DiskS3WriteMicroseconds':1401930,'DiskS3WriteRequestsCount':14,'S3CreateMultipartUpload':1,'S3UploadPart':3,'S3CompleteMultipartUpload':1,'S3PutObject':9,'DiskS3CreateMultipartUpload':1,'DiskS3UploadPart':3,'DiskS3CompleteMultipartUpload':1,'DiskS3PutObject':9,'WriteBufferFromS3Microseconds':1653634,'WriteBufferFromS3Bytes':79420269,'CachedWriteBufferCacheWriteBytes':79420269,'CachedWriteBufferCacheWriteMicroseconds':37003,'FilesystemCacheReserveMicroseconds':826,'FileSegmentCompleteMicroseconds':46,'FileSegmentWriteMicroseconds':35914,'FilesystemCacheHoldFileSegments':12,'FilesystemCacheUnusedHoldFileSegments':12,'MetadataFromKeeperCacheHit':18,'MetadataFromKeeperCacheMiss':8,'MetadataFromKeeperTransactionCommit':2,'MetadataFromKeeperOperations':8,'MetadataFromKeeperIndividualOperations':6,'SharedMergeTreeMetadataCacheHintLoadedFromCache':2,'LogTrace':54,'LogDebug':16,'LoggerElapsedNanoseconds':858534,'InterfaceHTTPReceiveBytes':129486972,'DiskConnectionsCreated':9,'DiskConnectionsReused':5,'DiskConnectionsPreserved':14,'DiskConnectionsExpired':1,'DiskConnectionsElapsedMicroseconds':35140,'HTTPConnectionsCreated':1,'HTTPConnectionsReused':1,'HTTPConnectionsPreserved':2,'HTTPConnectionsExpired':1,'HTTPConnectionsElapsedMicroseconds':91,'ReadWriteBufferFromHTTPRequestsSent':2,'ReadWriteBufferFromHTTPBytes':3342}"
  }
}
