{
  "client_machine": "m6i.8xlarge, 10000gib gp3",
  "server_system": "ClickHouse Cloud 24.10 30 vCPU and 120 GiB per replica / 3 replicas",
  "date": "2025-02-26",
  "interface": "http",
  "format": "NDJSON",
  "total_num_rows": 10000000,
  "batch_size": 500000,
  "sorted": true,
  "compressor": "lz4",
  "compression_type": "http compression",
  "server_metrics": {
    "db_name": "hits_http_ndjson_500000_sorted_lz4_2025_02_27_08_39",
    "table_name": "hits",
    "used_interface": "http",
    "used_transport_format": "NDJSON",
    "inserts": 20,
    "rows_per_insert": 500000,
    "total_inserted_rows": 10000000,
    "total_time_including_client_loop_s": 110,
    "total_received_bytes": 4535481405,
    "received_bytes_per_insert": 226774070,
    "total_received_bytes_readable": "4.22 GiB",
    "received_bytes_per_insert_readable": "216.27 MiB",
    "total_written_bytes_compressed": 1570745002,
    "written_bytes_compressed_per_insert": 78537250,
    "total_written_bytes_compressed_readable": "1.46 GiB",
    "written_bytes_compressed_per_insert_readable": "74.90 MiB",
    "total_insert_duration_s": 69.56,
    "total_network_receive_duration_s": 1.58,
    "total_block_sort_duration_s": 0.1,
    "total_storage_write_duration_s": 31.88,
    "total_cpu_s": 143.42,
    "num_delayed_inserts": 0,
    "total_delayed_inserts_ms": 0,
    "insert_duration_ms_50th": 3456.5,
    "insert_duration_ms_95th": 3573.75,
    "insert_duration_ms_99th": 4193.15,
    "network_receive_duration_ms_50th": 79.19,
    "network_receive_duration_ms_95th": 88.75,
    "network_receive_duration_ms_99th": 92.08,
    "block_sort_duration_ms_50th": 4.99,
    "block_sort_duration_ms_95th": 5.04,
    "block_sort_duration_ms_99th": 5.21,
    "storage_write_duration_ms_50th": 1572.53,
    "storage_write_duration_ms_95th": 1724.52,
    "storage_write_duration_ms_99th": 2347.62,
    "network_received_bytes_50th": 226731011,
    "network_received_bytes_95th": 227049753,
    "network_received_bytes_99th": 227053319,
    "network_received_bytes_50th_readable": "216.23 MiB",
    "network_received_bytes_95th_readable": "216.53 MiB",
    "network_received_bytes_99th_readable": "216.53 MiB",
    "mergetree_written_uncompressed_bytes_50th": 312465192,
    "mergetree_written_uncompressed_bytes_95th": 317866851,
    "mergetree_written_uncompressed_bytes_99th": 393248620,
    "mergetree_written_uncompressed_bytes_50th_readable": "297.99 MiB",
    "mergetree_written_uncompressed_bytes_95th_readable": "303.14 MiB",
    "mergetree_written_uncompressed_bytes_99th_readable": "375.03 MiB",
    "mergetree_written_compressed_bytes_50th": 78539614,
    "mergetree_written_compressed_bytes_95th": 78678884,
    "mergetree_written_compressed_bytes_99th": 78687983,
    "mergetree_written_compressed_bytes_50th_readable": "74.90 MiB",
    "mergetree_written_compressed_bytes_95th_readable": "75.03 MiB",
    "mergetree_written_compressed_bytes_99th_readable": "75.04 MiB",
    "memory_usage_bytes_50th": 1057424662,
    "memory_usage_bytes_95th": 1065644846,
    "memory_usage_bytes_99th": 1150867147,
    "memory_usage_50th_readable": "1008.44 MiB",
    "memory_usage_95th_readable": "1016.28 MiB",
    "memory_usage_99th_readable": "1.07 GiB",
    "cpu_ms_50th": 7208.52,
    "cpu_ms_95th": 7316.76,
    "cpu_ms_99th": 7320.27,
    "num_used_threads_50th": 18,
    "num_used_threads_95th": 18.350000000000005,
    "num_used_threads_99th": 23.66999999999999,
    "num_used_threads_concurrently_50th": 12,
    "num_used_threads_concurrently_95th": 12.05,
    "num_used_threads_concurrently_99th": 12.809999999999999,
    "profileevents_sample": "{'Query':1,'InsertQuery':1,'InitialQuery':1,'FileOpen':12,'WriteBufferFromFileDescriptorWrite':25,'WriteBufferFromFileDescriptorWriteBytes':78585964,'IOBufferAllocs':70,'IOBufferAllocBytes':458775142,'FunctionExecute':210,'DiskWriteElapsedMicroseconds':39841,'NetworkReceiveElapsedMicroseconds':78106,'NetworkReceiveBytes':226784437,'GlobalThreadPoolJobs':5,'LocalThreadPoolExpansions':4,'LocalThreadPoolThreadCreationMicroseconds':61,'LocalThreadPoolLockWaitMicroseconds':15,'LocalThreadPoolJobs':122,'InsertedRows':500000,'InsertedBytes':311149577,'ZooKeeperTransactions':12,'ZooKeeperCreate':2,'ZooKeeperRemove':2,'ZooKeeperMulti':8,'SelectedRows':500000,'SelectedBytes':311149577,'MergeTreeDataWriterRows':500000,'MergeTreeDataWriterUncompressedBytes':312540169,'MergeTreeDataWriterCompressedBytes':78580719,'MergeTreeDataWriterBlocks':2,'MergeTreeDataWriterBlocksAlreadySorted':2,'MergeTreeDataWriterSortingBlocksMicroseconds':5003,'MergeTreeDataWriterMergingBlocksMicroseconds':6,'InsertedCompactParts':2,'ContextLock':47,'RWLockAcquiredReadLocks':2,'PartsLockHoldMicroseconds':282,'RealTimeMicroseconds':10929479,'UserTimeMicroseconds':6828141,'SystemTimeMicroseconds':468744,'SoftPageFaults':336087,'OSCPUWaitMicroseconds':6084,'OSCPUVirtualTimeMicroseconds':7296734,'OSWriteBytes':78622720,'OSReadChars':163704,'OSWriteChars':157499204,'QueryProfilerRuns':19,'S3WriteMicroseconds':1301964,'S3WriteRequestsCount':14,'DiskS3WriteMicroseconds':1301964,'DiskS3WriteRequestsCount':14,'S3CreateMultipartUpload':1,'S3UploadPart':3,'S3CompleteMultipartUpload':1,'S3PutObject':9,'DiskS3CreateMultipartUpload':1,'DiskS3UploadPart':3,'DiskS3CompleteMultipartUpload':1,'DiskS3PutObject':9,'WriteBufferFromS3Microseconds':1528817,'WriteBufferFromS3Bytes':78585964,'CachedWriteBufferCacheWriteBytes':78585964,'CachedWriteBufferCacheWriteMicroseconds':41343,'FilesystemCacheReserveMicroseconds':772,'FileSegmentCompleteMicroseconds':47,'FileSegmentWriteMicroseconds':40288,'FilesystemCacheHoldFileSegments':12,'FilesystemCacheUnusedHoldFileSegments':12,'MetadataFromKeeperCacheHit':18,'MetadataFromKeeperCacheMiss':8,'MetadataFromKeeperTransactionCommit':2,'MetadataFromKeeperOperations':8,'MetadataFromKeeperIndividualOperations':6,'SharedMergeTreeMetadataCacheHintLoadedFromCache':2,'LogTrace':53,'LogDebug':15,'LoggerElapsedNanoseconds':757268,'InterfaceHTTPReceiveBytes':226784437,'SharedMergeTreeTryUpdateDiskMetadataCacheForPartMicroseconds':3052,'DiskConnectionsCreated':5,'DiskConnectionsReused':9,'DiskConnectionsPreserved':14,'DiskConnectionsElapsedMicroseconds':21316,'HTTPConnectionsCreated':1,'HTTPConnectionsReused':1,'HTTPConnectionsPreserved':2,'HTTPConnectionsExpired':1,'HTTPConnectionsElapsedMicroseconds':911,'ReadWriteBufferFromHTTPRequestsSent':2,'ReadWriteBufferFromHTTPBytes':3340}"
  }
}
