{
  "client_machine": "m6i.8xlarge, 10000gib gp3",
  "server_system": "ClickHouse Cloud 24.10 30 vCPU and 120 GiB per replica / 3 replicas",
  "date": "2025-02-27",
  "interface": "native",
  "format": "TabSeparatedWithNames",
  "total_num_rows": 10000000,
  "batch_size": 500000,
  "sorted": false,
  "compressor": "lz4",
  "compression_type": "network compression",
  "server_metrics": {
    "db_name": "hits_native_tabseparatedwithnames_500000_lz4_2025_02_27_11_03",
    "table_name": "hits",
    "used_interface": "native",
    "used_transport_format": "Native",
    "inserts": 20,
    "rows_per_insert": 500000,
    "total_inserted_rows": 10000000,
    "total_time_including_client_loop_s": 53,
    "total_received_bytes": 2738775567,
    "received_bytes_per_insert": 136938778,
    "total_received_bytes_readable": "2.55 GiB",
    "received_bytes_per_insert_readable": "130.59 MiB",
    "total_written_bytes_compressed": 1604658428,
    "written_bytes_compressed_per_insert": 80232921,
    "total_written_bytes_compressed_readable": "1.49 GiB",
    "written_bytes_compressed_per_insert_readable": "76.52 MiB",
    "total_insert_duration_s": 50.92,
    "total_network_receive_duration_s": 8.64,
    "total_block_sort_duration_s": 0.56,
    "total_storage_write_duration_s": 30.65,
    "total_cpu_s": 40.39,
    "num_delayed_inserts": 0,
    "total_delayed_inserts_ms": 0,
    "insert_duration_ms_50th": 2540,
    "insert_duration_ms_95th": 2636.3,
    "insert_duration_ms_99th": 2671.26,
    "network_receive_duration_ms_50th": 434.98,
    "network_receive_duration_ms_95th": 451.86,
    "network_receive_duration_ms_99th": 465.53,
    "block_sort_duration_ms_50th": 27.32,
    "block_sort_duration_ms_95th": 29.17,
    "block_sort_duration_ms_99th": 29.35,
    "storage_write_duration_ms_50th": 1533.9,
    "storage_write_duration_ms_95th": 1642.77,
    "storage_write_duration_ms_99th": 1711.74,
    "network_received_bytes_50th": 136911914,
    "network_received_bytes_95th": 137198815,
    "network_received_bytes_99th": 137205136,
    "network_received_bytes_50th_readable": "130.57 MiB",
    "network_received_bytes_95th_readable": "130.84 MiB",
    "network_received_bytes_99th_readable": "130.85 MiB",
    "mergetree_written_uncompressed_bytes_50th": 412210550,
    "mergetree_written_uncompressed_bytes_95th": 412637580,
    "mergetree_written_uncompressed_bytes_99th": 412669181,
    "mergetree_written_uncompressed_bytes_50th_readable": "393.11 MiB",
    "mergetree_written_uncompressed_bytes_95th_readable": "393.52 MiB",
    "mergetree_written_uncompressed_bytes_99th_readable": "393.55 MiB",
    "mergetree_written_compressed_bytes_50th": 80222622,
    "mergetree_written_compressed_bytes_95th": 80404104,
    "mergetree_written_compressed_bytes_99th": 80406787,
    "mergetree_written_compressed_bytes_50th_readable": "76.51 MiB",
    "mergetree_written_compressed_bytes_95th_readable": "76.68 MiB",
    "mergetree_written_compressed_bytes_99th_readable": "76.68 MiB",
    "memory_usage_bytes_50th": 731137710,
    "memory_usage_bytes_95th": 731308312,
    "memory_usage_bytes_99th": 731357607,
    "memory_usage_50th_readable": "697.27 MiB",
    "memory_usage_95th_readable": "697.43 MiB",
    "memory_usage_99th_readable": "697.48 MiB",
    "cpu_ms_50th": 2005.36,
    "cpu_ms_95th": 2121.56,
    "cpu_ms_99th": 2122.12,
    "num_used_threads_50th": 20,
    "num_used_threads_95th": 20,
    "num_used_threads_99th": 20,
    "num_used_threads_concurrently_50th": 11,
    "num_used_threads_concurrently_95th": 11,
    "num_used_threads_concurrently_99th": 11,
    "profileevents_sample": "{'Query':1,'InsertQuery':1,'InitialQuery':1,'FileOpen':19,'WriteBufferFromFileDescriptorWrite':36,'WriteBufferFromFileDescriptorWriteBytes':80150833,'ReadCompressedBytes':136854427,'CompressedReadBufferBlocks':323,'CompressedReadBufferBytes':300445713,'IOBufferAllocs':48,'IOBufferAllocBytes':109579354,'FunctionExecute':210,'DiskWriteElapsedMicroseconds':37643,'NetworkReceiveElapsedMicroseconds':441857,'NetworkSendElapsedMicroseconds':1591,'NetworkReceiveBytes':136854465,'NetworkSendBytes':132448,'LocalThreadPoolJobs':19,'InsertedRows':500000,'InsertedBytes':412078809,'ZooKeeperTransactions':15,'ZooKeeperCreate':2,'ZooKeeperRemove':2,'ZooKeeperGet':1,'ZooKeeperSet':1,'ZooKeeperMulti':9,'SelectedRows':500000,'SelectedBytes':412078809,'MergeTreeDataWriterRows':500000,'MergeTreeDataWriterUncompressedBytes':412078809,'MergeTreeDataWriterCompressedBytes':80145879,'MergeTreeDataWriterBlocks':2,'MergeTreeDataWriterSortingBlocksMicroseconds':26831,'MergeTreeDataWriterMergingBlocksMicroseconds':6,'InsertedCompactParts':2,'ContextLock':62,'RWLockAcquiredReadLocks':2,'PartsLockHoldMicroseconds':258,'RealTimeMicroseconds':3855085,'UserTimeMicroseconds':1605643,'SystemTimeMicroseconds':375658,'SoftPageFaults':203202,'OSCPUWaitMicroseconds':24,'OSCPUVirtualTimeMicroseconds':1981276,'OSWriteBytes':80224256,'OSReadChars':32839,'OSWriteChars':160640559,'QueryProfilerRuns':5,'S3WriteMicroseconds':1250104,'S3WriteRequestsCount':21,'DiskS3WriteMicroseconds':1250104,'DiskS3WriteRequestsCount':21,'S3CreateMultipartUpload':1,'S3UploadPart':2,'S3CompleteMultipartUpload':1,'S3PutObject':17,'DiskS3CreateMultipartUpload':1,'DiskS3UploadPart':2,'DiskS3CompleteMultipartUpload':1,'DiskS3PutObject':17,'WriteBufferFromS3Microseconds':1456310,'WriteBufferFromS3Bytes':80150833,'CachedWriteBufferCacheWriteBytes':80150833,'CachedWriteBufferCacheWriteMicroseconds':39781,'FilesystemCacheReserveMicroseconds':1275,'FileSegmentCompleteMicroseconds':66,'FileSegmentWriteMicroseconds':38192,'FilesystemCacheHoldFileSegments':19,'FilesystemCacheUnusedHoldFileSegments':19,'MetadataFromKeeperCacheHit':18,'MetadataFromKeeperCacheMiss':8,'MetadataFromKeeperTransactionCommit':2,'MetadataFromKeeperOperations':10,'MetadataFromKeeperIndividualOperations':8,'SharedMergeTreeMetadataCacheHintLoadedFromCache':2,'LogTrace':85,'LogDebug':15,'LoggerElapsedNanoseconds':835319,'InterfaceNativeSendBytes':132448,'InterfaceNativeReceiveBytes':136854465,'DiskConnectionsReused':21,'DiskConnectionsPreserved':21,'HTTPConnectionsCreated':1,'HTTPConnectionsReused':1,'HTTPConnectionsPreserved':2,'HTTPConnectionsExpired':1,'HTTPConnectionsElapsedMicroseconds':865,'ReadWriteBufferFromHTTPRequestsSent':2,'ReadWriteBufferFromHTTPBytes':5312,'ConcurrencyControlSlotsGranted':1,'ConcurrencyControlSlotsAcquired':1}"
  }
}
